{
  "LinkTitle": "D-2024-2907",
  "Status": "Intermediate",
  "InitialDMPReviewStatus": "Reviewed",
  "Funder": "FWO",
  "ProjectTitle": "From acoustic vibrations to neural oscillations: Using low-intensity transcranial focused ultrasound to control the rhythms of the brain",
  "InitialFeedbackHistory": "08/07/2024 Please add the ethical approval numbers when you update your DMP or final DMP that FWO will ask as part of the final report. [REDACTED] sharing data please check if your data is fully anonymous or whether you need to apply access restrictions, contact the ethical committee for advise if needed",
  "label": "good with suggestions"
}